BasicCombinational/fa/fa_gl.v
module fa_gl(a,b,c,s,c0);
input a,b,c;
output s,c0;
xor g1(x,a,b);
xor g2(s,x,c);
and g3(y,a,b);
and g4(z,x,c);
or g5(c0,y,z);
endmodule

BasicCombinational/fa/fa_tb.v
module fa_tb;
reg a,b,c;
wire s,c0;
fa_gl uut(.a(a),.b(b),.c(c),.c0(c0),.s(s));
initial begin 
$dumpfile ("fa.vcd");
$dumpvars(0,fa_tb);
$monitor("t=%0t,a=%b,b=%b,c=%b,s=%b,c0=%b",$time,a,b,c,s,c0);
a=0;b=0;c=0;#10
a=0;b=0;c=1;#10
a=0;b=1;c=0;#10
a=0;b=1;c=1;#10
a=1;b=0;c=0;#10
a=1;b=0;c=1;#10
a=1;b=1;c=0;#10
a=1;b=1;c=1;#10
$finish;
end
endmodule

BasicCombinational/fa/fa_tb.vcd
$date
	Fri Jun  5 09:45:22 2026
$end
$version
	Icarus Verilog
$end
$timescale
	1s
$end
$scope module fa_tb $end
$var wire 1 ! s $end
$var wire 1 " c0 $end
$var reg 1 # a $end
$var reg 1 $ b $end
$var reg 1 % c $end
$scope module uut $end
$var wire 1 # a $end
$var wire 1 $ b $end
$var wire 1 % c $end
$var wire 1 " c0 $end
$var wire 1 ! s $end
$var wire 1 & x $end
$var wire 1 ' y $end
$var wire 1 ( z $end
$upscope $end
$upscope $end
$enddefinitions $end
$comment Show the parameter values. $end
$dumpall
$end
#0
$dumpvars
0(
0'
0&
0%
0$
0#
0"
0!
$end
#10
1!
1%
#20
1&
0%
1$
#30
1"
0!
1(
1%
#40
0"
1!
0(
0%
0$
1#
#50
1"
0!
1(
1%
#60
0(
0&
1'
0%
1$
#70
1!
1%
