BasicCombinational/fs/fs_gl.v
module fs_gl(a,b,c,x,y,z,w,l,bw,d);
input a,b,c;
output x,y,z,w,l,bw,d;
xor g1(x,a,b);
not g2(y,x);
and g3(z,y,c);
not g4(w,a);
and g5(l,w,b);
or g6(bw,l,z);
xor g7(d,x,c);
endmodule

BasicCombinational/fs/fs_tb.v
module fs_tb;
reg a,b,c;
wire d,bw;
fs_gl uut(.a(a),.b(b),.c(c),.d(d),.bw(bw));
initial begin 
$dumpfile("fs.vcd");
$dumpvars(0,fs_tb);
$monitor("t=%0t,a=%b,b=%b,c=%b,d=%b,bw=%b",$time,a,b,c,d,bw);
a=0;b=0;c=0;#10
a=0;b=0;c=1;#10
a=0;b=1;c=0;#10
a=0;b=1;c=1;#10
a=1;b=0;c=0;#10
a=1;b=0;c=1;#10
a=1;b=1;c=0;#10
a=1;b=1;c=1;#10
$finish;
end 
endmodule

BasicCombinational/fs/fs.vcd
$date
	Fri Jun  5 09:53:46 2026
$end
$version
	Icarus Verilog
$end
$timescale
	1s
$end
$scope module fs_tb $end
$var wire 1 ! d $end
$var wire 1 " bw $end
$var reg 1 # a $end
$var reg 1 $ b $end
$var reg 1 % c $end
$scope module uut $end
$var wire 1 # a $end
$var wire 1 $ b $end
$var wire 1 " bw $end
$var wire 1 % c $end
$var wire 1 ! d $end
$var wire 1 & l $end
$var wire 1 ' w $end
$var wire 1 ( x $end
$var wire 1 ) y $end
$var wire 1 * z $end
$upscope $end
$upscope $end
$enddefinitions $end
$comment Show the parameter values. $end
$dumpall
$end
#0
$dumpvars
0*
1)
0(
1'
0&
0%
0$
0#
0"
0!
$end
#10
1"
1*
1!
1%
#20
0)
0*
1(
1&
0%
1$
#30
0!
1%
#40
0"
1!
0&
0'
0%
0$
1#
#50
0!
1%
#60
1)
0(
0%
1$
#70
1"
1*
1!
1%
